{
  "id": "var-001",
  "realm": "valley-of-variables",
  "title": "The Naming Ritual",
  "story": "Welcome, young Code Mage! The village elder approaches you with an ancient scroll. \"To begin your journey, you must learn the first spell of our craft - the Variable Declaration. Declare a string variable called 'heroName' and bind it to the name 'Aria'.\"",
  "type": "code-completion",
  "difficulty": 1,
  "xpReward": 50,
  "starterCode": "// Declare a string variable called 'heroName' and assign it the value \"Aria\"\n",
  "solution": "string heroName = \"Aria\";",
  "testCases": [
    { "description": "heroName should equal \"Aria\"", "assertion": "heroName == \"Aria\"" }
  ],
  "hints": [
    "In C#, we declare variables with: type name = value;",
    "Text values are called 'strings' and need double quotes",
    "The full syntax is: string heroName = \"Aria\";"
  ],
  "concepts": ["variables", "strings", "assignment"]
}
